[
  {
    "title": "[구로병원]영양팀 계약직일반업무원 모집(기간연장)",
    "start_dt": "2026-04-07T00:00+09:00",
    "end_dt": "2026-04-19T23:59+09:00",
    "dday": "D-1",
    "status": "접수중",
    "recu_idx": "106116",
    "announce_sn": "106116",
    "detail_url": "https://kumc.recruiter.co.kr/career/jobs/106116",
    "tags": [
      "구로병원",
      "일반채용",
      "신입"
    ],
    "hospital": "구로병원"
  },
  {
    "title": "[구로병원]총무팀 계약직직원(국군수도병원(국군외상센터)사업 관련 코디네이터 모집)(기간연장)",
    "start_dt": "2026-04-09T00:00+09:00",
    "end_dt": "2026-04-23T23:59+09:00",
    "dday": "D-5",
    "status": "접수중",
    "recu_idx": "106485",
    "announce_sn": "106485",
    "detail_url": "https://kumc.recruiter.co.kr/career/jobs/106485",
    "tags": [
      "구로병원",
      "일반채용",
      "신입"
    ],
    "hospital": "구로병원"
  },
  {
    "title": "[구로병원]간호간병통합서비스병동 계약직간호조무사 모집",
    "start_dt": "2026-04-17T00:00+09:00",
    "end_dt": "2026-04-23T23:59+09:00",
    "dday": "D-5",
    "status": "접수중",
    "recu_idx": "107237",
    "announce_sn": "107237",
    "detail_url": "https://kumc.recruiter.co.kr/career/jobs/107237",
    "tags": [
      "구로병원",
      "일반채용",
      "신입"
    ],
    "hospital": "구로병원"
  },
  {
    "title": "[구로병원]간호부 보호요원실 계약직일반업무원 모집",
    "start_dt": "2026-04-17T00:00+09:00",
    "end_dt": "2026-04-23T23:59+09:00",
    "dday": "D-5",
    "status": "접수중",
    "recu_idx": "107239",
    "announce_sn": "107239",
    "detail_url": "https://kumc.recruiter.co.kr/career/jobs/107239",
    "tags": [
      "구로병원",
      "일반채용",
      "신입"
    ],
    "hospital": "구로병원"
  },
  {
    "title": "[구로병원]호흡기내과 계약직임상병리사 모집",
    "start_dt": "2026-04-17T00:00+09:00",
    "end_dt": "2026-04-23T23:59+09:00",
    "dday": "D-5",
    "status": "접수중",
    "recu_idx": "107241",
    "announce_sn": "107241",
    "detail_url": "https://kumc.recruiter.co.kr/career/jobs/107241",
    "tags": [
      "구로병원",
      "일반채용",
      "신입"
    ],
    "hospital": "구로병원"
  },
  {
    "title": "[구로병원]약제팀 시간제 야간약사 모집",
    "start_dt": "2026-04-17T00:00+09:00",
    "end_dt": "2026-04-23T23:59+09:00",
    "dday": "D-5",
    "status": "접수중",
    "recu_idx": "107245",
    "announce_sn": "107245",
    "detail_url": "https://kumc.recruiter.co.kr/career/jobs/107245",
    "tags": [
      "구로병원",
      "일반채용",
      "신입"
    ],
    "hospital": "구로병원"
  },
  {
    "title": "[구로병원]임상시험지원팀 계약직간호사 모집",
    "start_dt": "2026-04-17T00:00+09:00",
    "end_dt": "2026-04-23T23:59+09:00",
    "dday": "D-5",
    "status": "접수중",
    "recu_idx": "107249",
    "announce_sn": "107249",
    "detail_url": "https://kumc.recruiter.co.kr/career/jobs/107249",
    "tags": [
      "구로병원",
      "일반채용",
      "신입"
    ],
    "hospital": "구로병원"
  },
  {
    "title": "[구로병원] 호흡기내과(결핵관리실) 계약직간호사 모집",
    "start_dt": "2026-04-17T00:00+09:00",
    "end_dt": "2026-04-23T23:59+09:00",
    "dday": "D-5",
    "status": "접수중",
    "recu_idx": "107334",
    "announce_sn": "107334",
    "detail_url": "https://kumc.recruiter.co.kr/career/jobs/107334",
    "tags": [
      "구로병원",
      "일반채용",
      "신입"
    ],
    "hospital": "구로병원"
  },
  {
    "title": "2026년도 고려대학교안암병원 소아청소년과 임상강사 모집",
    "start_dt": "2025-09-05T00:00+09:00",
    "end_dt": "2026-04-30T23:59+09:00",
    "dday": "D-12",
    "status": "접수중",
    "recu_idx": "82901",
    "announce_sn": "82901",
    "detail_url": "https://kumc.recruiter.co.kr/career/jobs/82901",
    "tags": [
      "안암병원",
      "일반채용",
      "신입"
    ],
    "hospital": "안암병원"
  }
]