[
  {
    "title": "[이화의료원] 2026년 상반기 이화여자대학교 의료원 비전임교원 초빙 공고",
    "start_dt": "2025-11-05T09:00:00+09:00",
    "end_dt": "2025-11-21T17:05:00+09:00",
    "dday": "D-11",
    "detail_url": "https://mokdong.eumc.ac.kr/view.do?bbs_no=28993&pageIndex=1&searchWord=&bid_status=I",
    "raw_lines": [
      "D-11",
      "[이화의료원] 2026년 상반기 이화여자대학교 의료원 비전임교원 초빙 공고",
      "2025-11-05 09:00:00 ~ 2025-11-21 17:05:00"
    ]
  },
  {
    "title": "2026년도 이대목동병원 전임의사(fellow) 초빙 공고",
    "start_dt": "2025-11-03T09:00:00+09:00",
    "end_dt": "2025-11-21T17:00:00+09:00",
    "dday": "D-11",
    "detail_url": "https://mokdong.eumc.ac.kr/view.do?bbs_no=28976&pageIndex=1&searchWord=&bid_status=I",
    "raw_lines": [
      "D-11",
      "2026년도 이대목동병원 전임의사(fellow) 초빙 공고",
      "2025-11-03 09:00:00 ~ 2025-11-21 17:00:00"
    ]
  },
  {
    "title": "[이화의료원] 국제의료사업팀 단기간 아르바이트(러시아어 코디네이터) 공개채용 공고",
    "start_dt": "2025-10-31T09:00:00+09:00",
    "end_dt": "2025-11-10T23:59:00+09:00",
    "dday": "D-0",
    "detail_url": "https://mokdong.eumc.ac.kr/view.do?bbs_no=28968&pageIndex=1&searchWord=&bid_status=I",
    "raw_lines": [
      "D-0",
      "[이화의료원] 국제의료사업팀 단기간 아르바이트(러시아어 코디네이터) 공개채용 공고",
      "2025-10-31 09:00:00 ~ 2025-11-10 23:59:00"
    ]
  }
]