[
  {
    "title": "안과검사실 임상병리사 경력직 채용",
    "period_text": "2026.07.13\n~\r\n\t\t\t\t\t\t\t2026.07.20",
    "start_dt": "2026-07-13T00:00:00+09:00",
    "end_dt": "2026-07-20T23:59:00+09:00",
    "deadline_text": "D-6",
    "status": "온라인접수진행중",
    "detail_url": "https://www.samsunghospital.com/home/recruit/recruitInfo/recruitNoticeView.do?RECRUIT_CD=2026HAC20020&cPage=1"
  },
  {
    "title": "방사선치료실 계약직 방사선사 채용(기간한정)",
    "period_text": "2026.07.13\n~\r\n\t\t\t\t\t\t\t2026.07.20",
    "start_dt": "2026-07-13T00:00:00+09:00",
    "end_dt": "2026-07-20T23:59:00+09:00",
    "deadline_text": "D-6",
    "status": "온라인접수진행중",
    "detail_url": "https://www.samsunghospital.com/home/recruit/recruitInfo/recruitNoticeView.do?RECRUIT_CD=2026HAC10021&cPage=1"
  },
  {
    "title": "간호본부 외래 계약직 전담간호사(외래기록) 채용",
    "period_text": "2026.07.13\n~\r\n\t\t\t\t\t\t\t2026.07.20",
    "start_dt": "2026-07-13T00:00:00+09:00",
    "end_dt": "2026-07-20T23:59:00+09:00",
    "deadline_text": "D-6",
    "status": "온라인접수진행중",
    "detail_url": "https://www.samsunghospital.com/home/recruit/recruitInfo/recruitNoticeView.do?RECRUIT_CD=2026HAB0084&cPage=1"
  },
  {
    "title": "의료정보팀 계약직 보건의료정보관리사 채용",
    "period_text": "2026.07.13\n~\r\n\t\t\t\t\t\t\t2026.07.20",
    "start_dt": "2026-07-13T00:00:00+09:00",
    "end_dt": "2026-07-20T23:59:00+09:00",
    "deadline_text": "D-6",
    "status": "온라인접수진행중",
    "detail_url": "https://www.samsunghospital.com/home/recruit/recruitInfo/recruitNoticeView.do?RECRUIT_CD=2026HAD60006&cPage=1"
  },
  {
    "title": "2026년도 하반기 레지던트 상급년차 모집",
    "period_text": "2026.07.13\n~\r\n\t\t\t\t\t\t\t2026.07.27",
    "start_dt": "2026-07-13T00:00:00+09:00",
    "end_dt": "2026-07-27T23:59:00+09:00",
    "deadline_text": "D-13",
    "status": "온라인접수진행중",
    "detail_url": "https://www.samsunghospital.com/home/recruit/recruitInfo/recruitNoticeView.do?RECRUIT_CD=2026EB0003&cPage=1"
  },
  {
    "title": "AX운영팀 계약직 사무직 채용",
    "period_text": "2026.07.13\n~\r\n\t\t\t\t\t\t\t2026.07.22",
    "start_dt": "2026-07-13T00:00:00+09:00",
    "end_dt": "2026-07-22T23:59:00+09:00",
    "deadline_text": "D-8",
    "status": "온라인접수진행중",
    "detail_url": "https://www.samsunghospital.com/home/recruit/recruitInfo/recruitNoticeView.do?RECRUIT_CD=2026AAH0061&cPage=1"
  },
  {
    "title": "정형외과 계약직 전담간호사(수술) 채용",
    "period_text": "2026.07.10\n~\r\n\t\t\t\t\t\t\t2026.07.20",
    "start_dt": "2026-07-10T00:00:00+09:00",
    "end_dt": "2026-07-20T23:59:00+09:00",
    "deadline_text": "D-6",
    "status": "온라인접수진행중",
    "detail_url": "https://www.samsunghospital.com/home/recruit/recruitInfo/recruitNoticeView.do?RECRUIT_CD=2026HAB0083&cPage=1"
  },
  {
    "title": "연구중심병원 육성 R&D사업 계약직 연구원 채용",
    "period_text": "2026.07.06\n~\r\n\t\t\t\t\t\t\t2026.07.20",
    "start_dt": "2026-07-06T00:00:00+09:00",
    "end_dt": "2026-07-20T23:59:00+09:00",
    "deadline_text": "D-6",
    "status": "온라인접수진행중",
    "detail_url": "https://www.samsunghospital.com/home/recruit/recruitInfo/recruitNoticeView.do?RECRUIT_CD=2026EAJ0022&cPage=1"
  },
  {
    "title": "2026년 외과(대장항문외과분과) 입원전담전문의 초빙 안내",
    "period_text": "2026.06.30\n~\r\n\t\t\t\t\t\t\t2026.07.14",
    "start_dt": "2026-06-30T00:00:00+09:00",
    "end_dt": "2026-07-14T23:59:00+09:00",
    "deadline_text": "오늘",
    "status": "온라인접수진행중",
    "detail_url": "https://www.samsunghospital.com/home/recruit/recruitInfo/recruitNoticeView.do?RECRUIT_CD=2026D0029&cPage=1"
  },
  {
    "title": "국제진료파트 계약직 간호사 채용(기간한정)(연장)",
    "period_text": "2026.06.30\n~\r\n\t\t\t\t\t\t\t2026.07.20",
    "start_dt": "2026-06-30T00:00:00+09:00",
    "end_dt": "2026-07-20T23:59:00+09:00",
    "deadline_text": "D-6",
    "status": "온라인접수진행중",
    "detail_url": "https://www.samsunghospital.com/home/recruit/recruitInfo/recruitNoticeView.do?RECRUIT_CD=2026HAB0081&cPage=1"
  },
  {
    "title": "2026년도 임상강사(Fellow) 9월 임용 초빙 안내",
    "period_text": "2026.06.22\n~\r\n\t\t\t\t\t\t\t2026.07.16",
    "start_dt": "2026-06-22T00:00:00+09:00",
    "end_dt": "2026-07-16T23:59:00+09:00",
    "deadline_text": "D-2",
    "status": "온라인접수진행중",
    "detail_url": "https://www.samsunghospital.com/home/recruit/recruitInfo/recruitNoticeView.do?RECRUIT_CD=2026D0030&cPage=2"
  }
]