[
  {
    "title": "D-2[이화의료원] 2026년 서울병원 간호부 정규직 경력간호사 공개채용 공고(혈관조영실, 심혈관조영실)",
    "period_text": "2026-03-30 09:00:00 ~ 2026-04-05 23:59:00",
    "start_dt": "2026-03-30T00:00:00+09:00",
    "end_dt": "2026-04-05T23:59:00+09:00",
    "detail_url": "https://seoul.eumc.ac.kr/view.do?bbs_no=30066&pageIndex=1&searchWord=&bid_status=I"
  },
  {
    "title": "D-58[서울병원] 간호부 계약직 기능원 공개채용 공고",
    "period_text": "2026-03-30 09:00:00 ~ 2026-05-31 17:00:00",
    "start_dt": "2026-03-30T00:00:00+09:00",
    "end_dt": "2026-05-31T23:59:00+09:00",
    "detail_url": "https://seoul.eumc.ac.kr/view.do?bbs_no=30064&pageIndex=1&searchWord=&bid_status=I"
  },
  {
    "title": "D-2[이화의료원] 서울병원 신경과(뇌혈류검사실) 정규직 임상병리사  공개채용 공고",
    "period_text": "2026-03-30 00:00:00 ~ 2026-04-05 23:59:00",
    "start_dt": "2026-03-30T00:00:00+09:00",
    "end_dt": "2026-04-05T23:59:00+09:00",
    "detail_url": "https://seoul.eumc.ac.kr/view.do?bbs_no=30061&pageIndex=1&searchWord=&bid_status=I"
  },
  {
    "title": "D-2[이화의료원] 서울병원 IRB 정규직 간호사 공개채용 공고",
    "period_text": "2026-03-30 00:00:00 ~ 2026-04-05 23:59:00",
    "start_dt": "2026-03-30T00:00:00+09:00",
    "end_dt": "2026-04-05T23:59:00+09:00",
    "detail_url": "https://seoul.eumc.ac.kr/view.do?bbs_no=30059&pageIndex=1&searchWord=&bid_status=I"
  }
]