[
  {
    "title": "2026년도 레지던트 합격자 등록 안내",
    "period_text": "2026-12-26 ~ 2026-12-26",
    "start_dt": "2026-12-26T00:00:00+09:00",
    "end_dt": "2026-12-26T23:59:00+09:00",
    "status": "접수준비중",
    "detail_url": "https://www.snuh.org/recruView.do?recruit_id=25177"
  },
  {
    "title": "서울대학교병원 친인척 채용인원 공개 (2025년 4분기)",
    "period_text": "2026-01-31 ~ 2026-02-13",
    "start_dt": "2026-01-31T00:00:00+09:00",
    "end_dt": "2026-02-13T23:59:00+09:00",
    "status": "접수준비중",
    "detail_url": "https://www.snuh.org/recruView.do?recruit_id=26020"
  },
  {
    "title": "연구교수 공개채용",
    "period_text": "2026-01-30 ~ 2026-02-06",
    "start_dt": "2026-01-30T00:00:00+09:00",
    "end_dt": "2026-02-06T23:59:00+09:00",
    "status": "공고",
    "detail_url": "https://www.snuh.org/recruView.do?recruit_id=26016"
  },
  {
    "title": "서울대학교병원 블라인드 직원채용 (대체근로자) 공고 (장애인 특별우대)",
    "period_text": "2026-01-29 ~ 2026-02-05",
    "start_dt": "2026-01-29T00:00:00+09:00",
    "end_dt": "2026-02-05T23:59:00+09:00",
    "status": "접수중",
    "detail_url": "https://www.snuh.org/recruView.do?recruit_id=26018"
  },
  {
    "title": "2026년 상반기 서울대학교병원 인턴 최종합격자 공고",
    "period_text": "2026-01-28 ~ 2026-02-10",
    "start_dt": "2026-01-28T00:00:00+09:00",
    "end_dt": "2026-02-10T23:59:00+09:00",
    "status": "공고",
    "detail_url": "https://www.snuh.org/recruView.do?recruit_id=26019"
  },
  {
    "title": "진료교수요원 및 진료의 공개채용",
    "period_text": "2026-01-28 ~ 2026-02-04",
    "start_dt": "2026-01-28T00:00:00+09:00",
    "end_dt": "2026-02-04T23:59:00+09:00",
    "status": "공고",
    "detail_url": "https://www.snuh.org/recruView.do?recruit_id=26015"
  }
]