[
  {
    "title": "간호부 기능직(조무-감염전담) 모집",
    "start_dt": "2026-03-05T17:00:00+09:00",
    "end_dt": "2026-03-11T23:00:00+09:00",
    "dday": "D-1",
    "detail_url": "https://recruit.amc.seoul.kr/recruit/career/view.do?recuIdx=5192&announceSn=20260098"
  },
  {
    "title": "간호부 기능직(조무)모집",
    "start_dt": "2026-03-05T17:00:00+09:00",
    "end_dt": "2026-03-11T23:00:00+09:00",
    "dday": "D-1",
    "detail_url": "https://recruit.amc.seoul.kr/recruit/career/view.do?recuIdx=5191&announceSn=20260097"
  },
  {
    "title": "약제팀 기능직(조무) 모집",
    "start_dt": "2026-03-04T16:00:00+09:00",
    "end_dt": "2026-03-11T23:00:00+09:00",
    "dday": "D-1",
    "detail_url": "https://recruit.amc.seoul.kr/recruit/career/view.do?recuIdx=5190&announceSn=20260096"
  },
  {
    "title": "시설팀 기술직(자동화/통신) 모집",
    "start_dt": "2026-03-09T15:00:00+09:00",
    "end_dt": "2026-03-15T23:00:00+09:00",
    "dday": "D-5",
    "detail_url": "https://recruit.amc.seoul.kr/recruit/career/view.do?recuIdx=5203&announceSn=20260109"
  },
  {
    "title": "시설팀 기술직(설비) 모집",
    "start_dt": "2026-03-09T15:00:00+09:00",
    "end_dt": "2026-03-15T23:00:00+09:00",
    "dday": "D-5",
    "detail_url": "https://recruit.amc.seoul.kr/recruit/career/view.do?recuIdx=5202&announceSn=20260108"
  },
  {
    "title": "시설팀 기술직(전기) 모집",
    "start_dt": "2026-03-09T14:00:00+09:00",
    "end_dt": "2026-03-15T23:00:00+09:00",
    "dday": "D-5",
    "detail_url": "https://recruit.amc.seoul.kr/recruit/career/view.do?recuIdx=5201&announceSn=20260107"
  },
  {
    "title": "어린이병원간호팀 간호사 모집",
    "start_dt": "2026-03-09T10:00:00+09:00",
    "end_dt": "2026-03-15T23:00:00+09:00",
    "dday": "D-5",
    "detail_url": "https://recruit.amc.seoul.kr/recruit/career/view.do?recuIdx=5196&announceSn=20260102"
  },
  {
    "title": "영상의학팀 간호사 모집",
    "start_dt": "2026-03-09T09:00:00+09:00",
    "end_dt": "2026-03-15T23:00:00+09:00",
    "dday": "D-5",
    "detail_url": "https://recruit.amc.seoul.kr/recruit/career/view.do?recuIdx=5194&announceSn=20260100"
  },
  {
    "title": "법무팀 변호사 모집",
    "start_dt": "2026-03-06T09:00:00+09:00",
    "end_dt": "2026-03-15T23:00:00+09:00",
    "dday": "D-5",
    "detail_url": "https://recruit.amc.seoul.kr/recruit/career/view.do?recuIdx=5193&announceSn=20260099"
  },
  {
    "title": "임상시험센터 기능직(연구보조) 모집",
    "start_dt": "2026-03-09T10:00:00+09:00",
    "end_dt": "2026-03-16T23:00:00+09:00",
    "dday": "D-6",
    "detail_url": "https://recruit.amc.seoul.kr/recruit/career/view.do?recuIdx=5197&announceSn=20260106"
  },
  {
    "title": "임상시험센터(CRC) 연구코디네이터 모집",
    "start_dt": "2026-03-09T09:00:00+09:00",
    "end_dt": "2026-03-16T23:00:00+09:00",
    "dday": "D-6",
    "detail_url": "https://recruit.amc.seoul.kr/recruit/career/view.do?recuIdx=5195&announceSn=20260101"
  },
  {
    "title": "내과 당직전담(촉탁의사) 초빙",
    "start_dt": "2026-03-09T18:00:00+09:00",
    "end_dt": "2026-03-29T18:00:00+09:00",
    "dday": "D-19",
    "detail_url": "https://recruit.amc.seoul.kr/recruit/career/view.do?recuIdx=5200&announceSn=20260105"
  },
  {
    "title": "서울아산병원 진료교수 초빙",
    "start_dt": "2026-03-09T18:00:00+09:00",
    "end_dt": "2026-03-29T18:00:00+09:00",
    "dday": "D-19",
    "detail_url": "https://recruit.amc.seoul.kr/recruit/career/view.do?recuIdx=5199&announceSn=20260104"
  },
  {
    "title": "서울아산병원 입원전담전문의(Hospitalist) 초빙",
    "start_dt": "2026-03-09T18:00:00+09:00",
    "end_dt": "2026-03-29T18:00:00+09:00",
    "dday": "D-19",
    "detail_url": "https://recruit.amc.seoul.kr/recruit/career/view.do?recuIdx=5198&announceSn=20260103"
  }
]