[
  {
    "title": "계약직 신입직원 [한방조제팀 한약사] 공개채용 모집공고",
    "start_dt": "2026-04-20T00:00:00+09:00",
    "end_dt": "2026-04-26T23:59:00+09:00",
    "dday": "D-5",
    "detail_url": "https://recruit.incruit.com/khmc/job/2604200011"
  },
  {
    "title": "계약직 신입직원 [호흡기알레르기내과 진료지원간호사] 공개채용 모집공고",
    "start_dt": "2026-04-17T00:00:00+09:00",
    "end_dt": "2026-04-21T23:59:00+09:00",
    "dday": "D-0",
    "detail_url": "https://recruit.incruit.com/khmc/job/2604170020"
  },
  {
    "title": "계약직 신입직원 [보험심사팀 아르바이트] 공개채용 모집",
    "start_dt": "2026-04-17T00:00:00+09:00",
    "end_dt": "2026-04-23T23:59:00+09:00",
    "dday": "D-2",
    "detail_url": "https://recruit.incruit.com/khmc/job/2604170006"
  },
  {
    "title": "계약직 신입직원 [조제팀 야간약사] 공개채용 모집공고",
    "start_dt": "2026-04-16T00:00:00+09:00",
    "end_dt": "2026-04-23T23:59:00+09:00",
    "dday": "D-2",
    "detail_url": "https://recruit.incruit.com/khmc/job/2604160009"
  },
  {
    "title": "계약직 신입직원 [진료협력팀 진료의뢰회송 간호사] 공개채용 모집공고",
    "start_dt": "2026-04-15T00:00:00+09:00",
    "end_dt": "2026-04-21T23:59:00+09:00",
    "dday": "D-0",
    "detail_url": "https://recruit.incruit.com/khmc/job/2604150006"
  },
  {
    "title": "계약직 신입직원 [조제팀 야간약사] 공개채용 모집공고",
    "start_dt": "2026-04-08T00:00:00+09:00",
    "end_dt": "2026-05-07T23:59:00+09:00",
    "dday": "D-16",
    "detail_url": "https://recruit.incruit.com/khmc/job/2604080017"
  }
]