[
  {
    "title": "간호본부 계약직 사원 채용",
    "start_dt": "2026-02-13T00:00:00+09:00",
    "end_dt": "2026-02-20T23:59:00+09:00",
    "dday": "D-1",
    "detail_url": "https://www.samsunghospital.com/home/recruit/recruitInfo/recruitNoticeView.do?RECRUIT_CD=2026AAHF0025&cPage=1"
  },
  {
    "title": "간호본부 계약직 3교대 보조원 채용(2월 3차)",
    "start_dt": "2026-02-13T00:00:00+09:00",
    "end_dt": "2026-02-20T23:59:00+09:00",
    "dday": "D-1",
    "detail_url": "https://www.samsunghospital.com/home/recruit/recruitInfo/recruitNoticeView.do?RECRUIT_CD=2026AAHF0024&cPage=1"
  },
  {
    "title": "건강의학본부 계약직 사원 채용",
    "start_dt": "2026-02-12T00:00:00+09:00",
    "end_dt": "2026-02-20T23:59:00+09:00",
    "dday": "D-1",
    "detail_url": "https://www.samsunghospital.com/home/recruit/recruitInfo/recruitNoticeView.do?RECRUIT_CD=2026AAHF0023&cPage=1"
  },
  {
    "title": "기관윤리심의사무국 담당자 경력직 채용",
    "start_dt": "2026-02-09T00:00:00+09:00",
    "end_dt": "2026-02-25T23:59:00+09:00",
    "dday": "D-6",
    "detail_url": "https://www.samsunghospital.com/home/recruit/recruitInfo/recruitNoticeView.do?RECRUIT_CD=2026AAH0009&cPage=1"
  }
]