[
  {
    "title": "D-5[서울병원] 영양팀 계약직 직원(영양사/조리사) 공개채용 공고",
    "start_dt": "2025-10-21T00:00:00+09:00",
    "end_dt": "2025-10-27T23:59:00+09:00",
    "dday": "D-5",
    "detail_url": "https://seoul.eumc.ac.kr/view.do?bbs_no=28860&pageIndex=1&searchWord=&bid_status=I"
  },
  {
    "title": "D-39[서울병원] 간호부 계약직 기능원 공개채용 공고",
    "start_dt": "2025-10-16T00:00:00+09:00",
    "end_dt": "2025-11-30T23:59:00+09:00",
    "dday": "D-39",
    "detail_url": "https://seoul.eumc.ac.kr/view.do?bbs_no=28817&pageIndex=1&searchWord=&bid_status=I"
  },
  {
    "title": "D-39[서울병원] 간호부 계약직 간호사(중앙공급실) 공개채용 공고",
    "start_dt": "2025-10-16T00:00:00+09:00",
    "end_dt": "2025-11-30T23:59:00+09:00",
    "dday": "D-39",
    "detail_url": "https://seoul.eumc.ac.kr/view.do?bbs_no=28814&pageIndex=1&searchWord=&bid_status=I"
  },
  {
    "title": "D-0[이화의료원] 서울병원 영상의학과 정규직 방사선사(신입) 공개채용 공고",
    "start_dt": "2025-10-16T00:00:00+09:00",
    "end_dt": "2025-10-22T23:59:00+09:00",
    "dday": "D-0",
    "detail_url": "https://seoul.eumc.ac.kr/view.do?bbs_no=28810&pageIndex=1&searchWord=&bid_status=I"
  },
  {
    "title": "D-39[서울병원] 간호부 계약직 간호사(외래) 공개채용 공고",
    "start_dt": "2025-10-13T00:00:00+09:00",
    "end_dt": "2025-11-30T23:59:00+09:00",
    "dday": "D-39",
    "detail_url": "https://seoul.eumc.ac.kr/view.do?bbs_no=28790&pageIndex=1&searchWord=&bid_status=I"
  },
  {
    "title": "D-5[서울병원] 약제팀 계약직 야간약사 공개채용 공고",
    "start_dt": "2025-10-02T00:00:00+09:00",
    "end_dt": "2025-10-27T23:59:00+09:00",
    "dday": "D-5",
    "detail_url": "https://seoul.eumc.ac.kr/view.do?bbs_no=28757&pageIndex=1&searchWord=&bid_status=I"
  },
  {
    "title": "D-5[서울병원] 총무팀 계약직 환자이송원 공개채용 공고",
    "start_dt": "2025-09-30T00:00:00+09:00",
    "end_dt": "2025-10-27T23:59:00+09:00",
    "dday": "D-5",
    "detail_url": "https://seoul.eumc.ac.kr/view.do?bbs_no=28676&pageIndex=1&searchWord=&bid_status=I"
  },
  {
    "title": "D-9[서울병원] 간호부 계약직 간호사(외래) 공개채용 공고",
    "start_dt": "2025-08-13T00:00:00+09:00",
    "end_dt": "2025-10-31T23:59:00+09:00",
    "dday": "D-9",
    "detail_url": "https://seoul.eumc.ac.kr/view.do?bbs_no=28282&pageIndex=1&searchWord=&bid_status=I"
  },
  {
    "title": "D-9[이화의료원] 응급실 내과 당직의(야간) 초빙 공고",
    "start_dt": "2025-07-23T00:00:00+09:00",
    "end_dt": "2025-10-31T23:59:00+09:00",
    "dday": "D-9",
    "detail_url": "https://seoul.eumc.ac.kr/view.do?bbs_no=28068&pageIndex=1&searchWord=&bid_status=I"
  }
]