[
  {
    "title": "2026년도 상반기 레지던트 상급년차 모집 공고",
    "start_dt": "2026-01-15T09:00:00+09:00",
    "end_dt": "2026-01-28T17:00:00+09:00",
    "dday": "D-12",
    "detail_url": "https://snubh.recruiter.co.kr/app/jobnotice/view?systemKindCode=MRS2&jobnoticeSn=240443"
  },
  {
    "title": "신입(사무직, 보건직) 직원 채용공고",
    "start_dt": "2026-01-14T12:00:00+09:00",
    "end_dt": "2026-01-23T23:59:00+09:00",
    "dday": "D-7",
    "detail_url": "https://snubh.recruiter.co.kr/app/jobnotice/view?systemKindCode=MRS2&jobnoticeSn=240356"
  },
  {
    "title": "경력(기술직) 직원 채용공고",
    "start_dt": "2026-01-14T12:00:00+09:00",
    "end_dt": "2026-01-23T23:59:00+09:00",
    "dday": "D-7",
    "detail_url": "https://snubh.recruiter.co.kr/app/jobnotice/view?systemKindCode=MRS2&jobnoticeSn=240355"
  },
  {
    "title": "경력(사무직) 직원 채용공고",
    "start_dt": "2026-01-14T12:00:00+09:00",
    "end_dt": "2026-01-23T23:59:00+09:00",
    "dday": "D-7",
    "detail_url": "https://snubh.recruiter.co.kr/app/jobnotice/view?systemKindCode=MRS2&jobnoticeSn=240350"
  },
  {
    "title": "26년 1월 신입(업무지원직 장애인) 직원 채용 공고",
    "start_dt": "2026-01-14T09:00:00+09:00",
    "end_dt": "2026-01-23T23:59:00+09:00",
    "dday": "D-7",
    "detail_url": "https://snubh.recruiter.co.kr/app/jobnotice/view?systemKindCode=MRS2&jobnoticeSn=240020"
  },
  {
    "title": "26년 1월 신입(업무지원직) 직원 채용 공고",
    "start_dt": "2026-01-14T09:00:00+09:00",
    "end_dt": "2026-01-23T23:59:00+09:00",
    "dday": "D-7",
    "detail_url": "https://snubh.recruiter.co.kr/app/jobnotice/view?systemKindCode=MRS2&jobnoticeSn=240006"
  },
  {
    "title": "2026년도 진료전문의 및 진료일반의 정기채용",
    "start_dt": "2026-01-12T10:00:00+09:00",
    "end_dt": "2026-01-21T17:00:00+09:00",
    "dday": "D-5",
    "detail_url": "https://snubh.recruiter.co.kr/app/jobnotice/view?systemKindCode=MRS2&jobnoticeSn=239836"
  },
  {
    "title": "2026년도 진료교수요원 정기채용",
    "start_dt": "2026-01-12T10:00:00+09:00",
    "end_dt": "2026-01-21T17:00:00+09:00",
    "dday": "D-5",
    "detail_url": "https://snubh.recruiter.co.kr/app/jobnotice/view?systemKindCode=MRS2&jobnoticeSn=239826"
  }
]