[
  {
    "title": "단시간연구전담직(의생명연구원) 채용공고",
    "start_dt": "2026-02-04T13:00:00+09:00",
    "end_dt": "2026-02-13T17:00:00+09:00",
    "dday": "D-8",
    "detail_url": "https://snubh.recruiter.co.kr/app/jobnotice/view?systemKindCode=MRS2&jobnoticeSn=243079"
  },
  {
    "title": "진료전문의(정형외과, 권역응급의료센터, 응급의학과), 진료일반의(마취통증의학과, 임상약리학과) 채용 공고",
    "start_dt": "2026-02-04T13:00:00+09:00",
    "end_dt": "2026-02-13T17:00:00+09:00",
    "dday": "D-8",
    "detail_url": "https://snubh.recruiter.co.kr/app/jobnotice/view?systemKindCode=MRS2&jobnoticeSn=243073"
  }
]